{
  "/authenticate-59" : {
    "transaction" : "/authenticate-59",
    "sampleCount" : 1,
    "errorCount" : 0,
    "errorPct" : 0.0,
    "meanResTime" : 36.0,
    "medianResTime" : 36.0,
    "minResTime" : 36.0,
    "maxResTime" : 36.0,
    "pct1ResTime" : 36.0,
    "pct2ResTime" : 36.0,
    "pct3ResTime" : 36.0,
    "throughput" : 27.777777777777775,
    "receivedKBytesPerSec" : 104.27517361111111,
    "sentKBytesPerSec" : 66.32486979166667
  },
  "/authenticate-59-1" : {
    "transaction" : "/authenticate-59-1",
    "sampleCount" : 1,
    "errorCount" : 0,
    "errorPct" : 0.0,
    "meanResTime" : 16.0,
    "medianResTime" : 16.0,
    "minResTime" : 16.0,
    "maxResTime" : 16.0,
    "pct1ResTime" : 16.0,
    "pct2ResTime" : 16.0,
    "pct3ResTime" : 16.0,
    "throughput" : 62.5,
    "receivedKBytesPerSec" : 173.9501953125,
    "sentKBytesPerSec" : 75.37841796875
  },
  "/secure-60" : {
    "transaction" : "/secure-60",
    "sampleCount" : 1,
    "errorCount" : 0,
    "errorPct" : 0.0,
    "meanResTime" : 10.0,
    "medianResTime" : 10.0,
    "minResTime" : 10.0,
    "maxResTime" : 10.0,
    "pct1ResTime" : 10.0,
    "pct2ResTime" : 10.0,
    "pct3ResTime" : 10.0,
    "throughput" : 100.0,
    "receivedKBytesPerSec" : 204.4921875,
    "sentKBytesPerSec" : 105.56640625
  },
  "Debug Sampler" : {
    "transaction" : "Debug Sampler",
    "sampleCount" : 1,
    "errorCount" : 0,
    "errorPct" : 0.0,
    "meanResTime" : 1.0,
    "medianResTime" : 1.0,
    "minResTime" : 1.0,
    "maxResTime" : 1.0,
    "pct1ResTime" : 1.0,
    "pct2ResTime" : 1.0,
    "pct3ResTime" : 1.0,
    "throughput" : 1000.0,
    "receivedKBytesPerSec" : 443.359375,
    "sentKBytesPerSec" : 0.0
  },
  "/authenticate-59-0" : {
    "transaction" : "/authenticate-59-0",
    "sampleCount" : 1,
    "errorCount" : 0,
    "errorPct" : 0.0,
    "meanResTime" : 19.0,
    "medianResTime" : 19.0,
    "minResTime" : 19.0,
    "maxResTime" : 19.0,
    "pct1ResTime" : 19.0,
    "pct2ResTime" : 19.0,
    "pct3ResTime" : 19.0,
    "throughput" : 52.63157894736842,
    "receivedKBytesPerSec" : 51.08963815789474,
    "sentKBytesPerSec" : 62.19161184210527
  },
  "Total" : {
    "transaction" : "Total",
    "sampleCount" : 9,
    "errorCount" : 0,
    "errorPct" : 0.0,
    "meanResTime" : 93.44444444444444,
    "medianResTime" : 16.0,
    "minResTime" : 1.0,
    "maxResTime" : 717.0,
    "pct1ResTime" : 717.0,
    "pct2ResTime" : 717.0,
    "pct3ResTime" : 717.0,
    "throughput" : 10.452961672473869,
    "receivedKBytesPerSec" : 25.134291521486645,
    "sentKBytesPerSec" : 12.283591027874564
  },
  "/logout-73-0" : {
    "transaction" : "/logout-73-0",
    "sampleCount" : 1,
    "errorCount" : 0,
    "errorPct" : 0.0,
    "meanResTime" : 11.0,
    "medianResTime" : 11.0,
    "minResTime" : 11.0,
    "maxResTime" : 11.0,
    "pct1ResTime" : 11.0,
    "pct2ResTime" : 11.0,
    "pct3ResTime" : 11.0,
    "throughput" : 90.9090909090909,
    "receivedKBytesPerSec" : 85.31605113636364,
    "sentKBytesPerSec" : 96.05823863636364
  },
  "/login-52 - multiple reg ex" : {
    "transaction" : "/login-52 - multiple reg ex",
    "sampleCount" : 1,
    "errorCount" : 0,
    "errorPct" : 0.0,
    "meanResTime" : 717.0,
    "medianResTime" : 717.0,
    "minResTime" : 717.0,
    "maxResTime" : 717.0,
    "pct1ResTime" : 717.0,
    "pct2ResTime" : 717.0,
    "pct3ResTime" : 717.0,
    "throughput" : 1.3947001394700138,
    "receivedKBytesPerSec" : 4.374782078103208,
    "sentKBytesPerSec" : 0.6360595362622037
  },
  "/logout-73" : {
    "transaction" : "/logout-73",
    "sampleCount" : 1,
    "errorCount" : 0,
    "errorPct" : 0.0,
    "meanResTime" : 21.0,
    "medianResTime" : 21.0,
    "minResTime" : 21.0,
    "maxResTime" : 21.0,
    "pct1ResTime" : 21.0,
    "pct2ResTime" : 21.0,
    "pct3ResTime" : 21.0,
    "throughput" : 47.61904761904761,
    "receivedKBytesPerSec" : 202.56696428571428,
    "sentKBytesPerSec" : 102.12053571428571
  },
  "/logout-73-1" : {
    "transaction" : "/logout-73-1",
    "sampleCount" : 1,
    "errorCount" : 0,
    "errorPct" : 0.0,
    "meanResTime" : 10.0,
    "medianResTime" : 10.0,
    "minResTime" : 10.0,
    "maxResTime" : 10.0,
    "pct1ResTime" : 10.0,
    "pct2ResTime" : 10.0,
    "pct3ResTime" : 10.0,
    "throughput" : 100.0,
    "receivedKBytesPerSec" : 331.54296875,
    "sentKBytesPerSec" : 108.7890625
  }
}