{
  "/authenticate-59" : {
    "transaction" : "/authenticate-59",
    "sampleCount" : 1,
    "errorCount" : 0,
    "errorPct" : 0.0,
    "meanResTime" : 175.0,
    "medianResTime" : 175.0,
    "minResTime" : 175.0,
    "maxResTime" : 175.0,
    "pct1ResTime" : 175.0,
    "pct2ResTime" : 175.0,
    "pct3ResTime" : 175.0,
    "throughput" : 5.714285714285714,
    "receivedKBytesPerSec" : 21.450892857142858,
    "sentKBytesPerSec" : 13.643973214285715
  },
  "/authenticate-59-1" : {
    "transaction" : "/authenticate-59-1",
    "sampleCount" : 1,
    "errorCount" : 0,
    "errorPct" : 0.0,
    "meanResTime" : 89.0,
    "medianResTime" : 89.0,
    "minResTime" : 89.0,
    "maxResTime" : 89.0,
    "pct1ResTime" : 89.0,
    "pct2ResTime" : 89.0,
    "pct3ResTime" : 89.0,
    "throughput" : 11.235955056179774,
    "receivedKBytesPerSec" : 31.271945224719104,
    "sentKBytesPerSec" : 13.551176264044944
  },
  "/secure-60" : {
    "transaction" : "/secure-60",
    "sampleCount" : 1,
    "errorCount" : 0,
    "errorPct" : 0.0,
    "meanResTime" : 82.0,
    "medianResTime" : 82.0,
    "minResTime" : 82.0,
    "maxResTime" : 82.0,
    "pct1ResTime" : 82.0,
    "pct2ResTime" : 82.0,
    "pct3ResTime" : 82.0,
    "throughput" : 12.195121951219512,
    "receivedKBytesPerSec" : 24.938071646341463,
    "sentKBytesPerSec" : 12.873951981707316
  },
  "Debug Sampler" : {
    "transaction" : "Debug Sampler",
    "sampleCount" : 1,
    "errorCount" : 0,
    "errorPct" : 0.0,
    "meanResTime" : 2.0,
    "medianResTime" : 2.0,
    "minResTime" : 2.0,
    "maxResTime" : 2.0,
    "pct1ResTime" : 2.0,
    "pct2ResTime" : 2.0,
    "pct3ResTime" : 2.0,
    "throughput" : 500.0,
    "receivedKBytesPerSec" : 222.16796875,
    "sentKBytesPerSec" : 0.0
  },
  "/authenticate-59-0" : {
    "transaction" : "/authenticate-59-0",
    "sampleCount" : 1,
    "errorCount" : 0,
    "errorPct" : 0.0,
    "meanResTime" : 84.0,
    "medianResTime" : 84.0,
    "minResTime" : 84.0,
    "maxResTime" : 84.0,
    "pct1ResTime" : 84.0,
    "pct2ResTime" : 84.0,
    "pct3ResTime" : 84.0,
    "throughput" : 11.904761904761903,
    "receivedKBytesPerSec" : 11.555989583333332,
    "sentKBytesPerSec" : 14.067150297619047
  },
  "Total" : {
    "transaction" : "Total",
    "sampleCount" : 9,
    "errorCount" : 0,
    "errorPct" : 0.0,
    "meanResTime" : 157.33333333333334,
    "medianResTime" : 84.0,
    "minResTime" : 2.0,
    "maxResTime" : 657.0,
    "pct1ResTime" : 657.0,
    "pct2ResTime" : 657.0,
    "pct3ResTime" : 657.0,
    "throughput" : 8.1008100810081,
    "receivedKBytesPerSec" : 19.47938934518452,
    "sentKBytesPerSec" : 9.519506638163817
  },
  "/logout-73-0" : {
    "transaction" : "/logout-73-0",
    "sampleCount" : 1,
    "errorCount" : 0,
    "errorPct" : 0.0,
    "meanResTime" : 82.0,
    "medianResTime" : 82.0,
    "minResTime" : 82.0,
    "maxResTime" : 82.0,
    "pct1ResTime" : 82.0,
    "pct2ResTime" : 82.0,
    "pct3ResTime" : 82.0,
    "throughput" : 12.195121951219512,
    "receivedKBytesPerSec" : 11.44483612804878,
    "sentKBytesPerSec" : 12.885861280487804
  },
  "/login-52 - multiple reg ex" : {
    "transaction" : "/login-52 - multiple reg ex",
    "sampleCount" : 1,
    "errorCount" : 0,
    "errorPct" : 0.0,
    "meanResTime" : 657.0,
    "medianResTime" : 657.0,
    "minResTime" : 657.0,
    "maxResTime" : 657.0,
    "pct1ResTime" : 657.0,
    "pct2ResTime" : 657.0,
    "pct3ResTime" : 657.0,
    "throughput" : 1.5220700152207,
    "receivedKBytesPerSec" : 4.774305555555555,
    "sentKBytesPerSec" : 0.6941471651445966
  },
  "/logout-73" : {
    "transaction" : "/logout-73",
    "sampleCount" : 1,
    "errorCount" : 0,
    "errorPct" : 0.0,
    "meanResTime" : 164.0,
    "medianResTime" : 164.0,
    "minResTime" : 164.0,
    "maxResTime" : 164.0,
    "pct1ResTime" : 164.0,
    "pct2ResTime" : 164.0,
    "pct3ResTime" : 164.0,
    "throughput" : 6.097560975609756,
    "receivedKBytesPerSec" : 25.938452743902438,
    "sentKBytesPerSec" : 13.07641006097561
  },
  "/logout-73-1" : {
    "transaction" : "/logout-73-1",
    "sampleCount" : 1,
    "errorCount" : 0,
    "errorPct" : 0.0,
    "meanResTime" : 81.0,
    "medianResTime" : 81.0,
    "minResTime" : 81.0,
    "maxResTime" : 81.0,
    "pct1ResTime" : 81.0,
    "pct2ResTime" : 81.0,
    "pct3ResTime" : 81.0,
    "throughput" : 12.345679012345679,
    "receivedKBytesPerSec" : 40.931230709876544,
    "sentKBytesPerSec" : 13.430748456790123
  }
}