{
  "/authenticate-59" : {
    "transaction" : "/authenticate-59",
    "sampleCount" : 1,
    "errorCount" : 0,
    "errorPct" : 0.0,
    "meanResTime" : 82.0,
    "medianResTime" : 82.0,
    "minResTime" : 82.0,
    "maxResTime" : 82.0,
    "pct1ResTime" : 82.0,
    "pct2ResTime" : 82.0,
    "pct3ResTime" : 82.0,
    "throughput" : 12.195121951219512,
    "receivedKBytesPerSec" : 45.77934451219512,
    "sentKBytesPerSec" : 29.118235518292682
  },
  "/authenticate-59-1" : {
    "transaction" : "/authenticate-59-1",
    "sampleCount" : 1,
    "errorCount" : 0,
    "errorPct" : 0.0,
    "meanResTime" : 39.0,
    "medianResTime" : 39.0,
    "minResTime" : 39.0,
    "maxResTime" : 39.0,
    "pct1ResTime" : 39.0,
    "pct2ResTime" : 39.0,
    "pct3ResTime" : 39.0,
    "throughput" : 25.64102564102564,
    "receivedKBytesPerSec" : 71.3641826923077,
    "sentKBytesPerSec" : 30.924479166666668
  },
  "/secure-60" : {
    "transaction" : "/secure-60",
    "sampleCount" : 1,
    "errorCount" : 0,
    "errorPct" : 0.0,
    "meanResTime" : 38.0,
    "medianResTime" : 38.0,
    "minResTime" : 38.0,
    "maxResTime" : 38.0,
    "pct1ResTime" : 38.0,
    "pct2ResTime" : 38.0,
    "pct3ResTime" : 38.0,
    "throughput" : 26.31578947368421,
    "receivedKBytesPerSec" : 53.81373355263158,
    "sentKBytesPerSec" : 27.780633223684212
  },
  "Debug Sampler" : {
    "transaction" : "Debug Sampler",
    "sampleCount" : 1,
    "errorCount" : 0,
    "errorPct" : 0.0,
    "meanResTime" : 0.0,
    "medianResTime" : 0.0,
    "minResTime" : 0.0,
    "maxResTime" : 0.0,
    "pct1ResTime" : 0.0,
    "pct2ResTime" : 0.0,
    "pct3ResTime" : 0.0,
    "throughput" : "Infinity",
    "receivedKBytesPerSec" : "Infinity",
    "sentKBytesPerSec" : "NaN"
  },
  "/authenticate-59-0" : {
    "transaction" : "/authenticate-59-0",
    "sampleCount" : 1,
    "errorCount" : 0,
    "errorPct" : 0.0,
    "meanResTime" : 41.0,
    "medianResTime" : 41.0,
    "minResTime" : 41.0,
    "maxResTime" : 41.0,
    "pct1ResTime" : 41.0,
    "pct2ResTime" : 41.0,
    "pct3ResTime" : 41.0,
    "throughput" : 24.390243902439025,
    "receivedKBytesPerSec" : 23.675685975609756,
    "sentKBytesPerSec" : 28.820503048780488
  },
  "Total" : {
    "transaction" : "Total",
    "sampleCount" : 9,
    "errorCount" : 0,
    "errorPct" : 0.0,
    "meanResTime" : 89.44444444444444,
    "medianResTime" : 39.0,
    "minResTime" : 0.0,
    "maxResTime" : 451.0,
    "pct1ResTime" : 451.0,
    "pct2ResTime" : 451.0,
    "pct3ResTime" : 451.0,
    "throughput" : 13.333333333333334,
    "receivedKBytesPerSec" : 32.06163194444444,
    "sentKBytesPerSec" : 15.668402777777777
  },
  "/logout-73-0" : {
    "transaction" : "/logout-73-0",
    "sampleCount" : 1,
    "errorCount" : 0,
    "errorPct" : 0.0,
    "meanResTime" : 39.0,
    "medianResTime" : 39.0,
    "minResTime" : 39.0,
    "maxResTime" : 39.0,
    "pct1ResTime" : 39.0,
    "pct2ResTime" : 39.0,
    "pct3ResTime" : 39.0,
    "throughput" : 25.64102564102564,
    "receivedKBytesPerSec" : 24.063501602564102,
    "sentKBytesPerSec" : 27.093349358974358
  },
  "/login-52 - multiple reg ex" : {
    "transaction" : "/login-52 - multiple reg ex",
    "sampleCount" : 1,
    "errorCount" : 0,
    "errorPct" : 0.0,
    "meanResTime" : 451.0,
    "medianResTime" : 451.0,
    "minResTime" : 451.0,
    "maxResTime" : 451.0,
    "pct1ResTime" : 451.0,
    "pct2ResTime" : 451.0,
    "pct3ResTime" : 451.0,
    "throughput" : 2.2172949002217295,
    "receivedKBytesPerSec" : 6.955030487804878,
    "sentKBytesPerSec" : 1.0112077328159645
  },
  "/logout-73" : {
    "transaction" : "/logout-73",
    "sampleCount" : 1,
    "errorCount" : 0,
    "errorPct" : 0.0,
    "meanResTime" : 77.0,
    "medianResTime" : 77.0,
    "minResTime" : 77.0,
    "maxResTime" : 77.0,
    "pct1ResTime" : 77.0,
    "pct2ResTime" : 77.0,
    "pct3ResTime" : 77.0,
    "throughput" : 12.987012987012989,
    "receivedKBytesPerSec" : 55.245535714285715,
    "sentKBytesPerSec" : 27.851055194805195
  },
  "/logout-73-1" : {
    "transaction" : "/logout-73-1",
    "sampleCount" : 1,
    "errorCount" : 0,
    "errorPct" : 0.0,
    "meanResTime" : 38.0,
    "medianResTime" : 38.0,
    "minResTime" : 38.0,
    "maxResTime" : 38.0,
    "pct1ResTime" : 38.0,
    "pct2ResTime" : 38.0,
    "pct3ResTime" : 38.0,
    "throughput" : 26.31578947368421,
    "receivedKBytesPerSec" : 87.24814967105263,
    "sentKBytesPerSec" : 28.628700657894736
  }
}