{
  "/authenticate-59" : {
    "transaction" : "/authenticate-59",
    "sampleCount" : 1,
    "errorCount" : 0,
    "errorPct" : 0.0,
    "meanResTime" : 26.0,
    "medianResTime" : 26.0,
    "minResTime" : 26.0,
    "maxResTime" : 26.0,
    "pct1ResTime" : 26.0,
    "pct2ResTime" : 26.0,
    "pct3ResTime" : 26.0,
    "throughput" : 38.46153846153847,
    "receivedKBytesPerSec" : 182.91766826923077,
    "sentKBytesPerSec" : 91.83443509615385
  },
  "/authenticate-59-1" : {
    "transaction" : "/authenticate-59-1",
    "sampleCount" : 1,
    "errorCount" : 0,
    "errorPct" : 0.0,
    "meanResTime" : 11.0,
    "medianResTime" : 11.0,
    "minResTime" : 11.0,
    "maxResTime" : 11.0,
    "pct1ResTime" : 11.0,
    "pct2ResTime" : 11.0,
    "pct3ResTime" : 11.0,
    "throughput" : 90.9090909090909,
    "receivedKBytesPerSec" : 298.5617897727273,
    "sentKBytesPerSec" : 109.64133522727273
  },
  "/secure-60" : {
    "transaction" : "/secure-60",
    "sampleCount" : 1,
    "errorCount" : 0,
    "errorPct" : 0.0,
    "meanResTime" : 11.0,
    "medianResTime" : 11.0,
    "minResTime" : 11.0,
    "maxResTime" : 11.0,
    "pct1ResTime" : 11.0,
    "pct2ResTime" : 11.0,
    "pct3ResTime" : 11.0,
    "throughput" : 90.9090909090909,
    "receivedKBytesPerSec" : 231.4453125,
    "sentKBytesPerSec" : 95.96946022727273
  },
  "Debug Sampler" : {
    "transaction" : "Debug Sampler",
    "sampleCount" : 1,
    "errorCount" : 0,
    "errorPct" : 0.0,
    "meanResTime" : 1.0,
    "medianResTime" : 1.0,
    "minResTime" : 1.0,
    "maxResTime" : 1.0,
    "pct1ResTime" : 1.0,
    "pct2ResTime" : 1.0,
    "pct3ResTime" : 1.0,
    "throughput" : 1000.0,
    "receivedKBytesPerSec" : 444.3359375,
    "sentKBytesPerSec" : 0.0
  },
  "/authenticate-59-0" : {
    "transaction" : "/authenticate-59-0",
    "sampleCount" : 1,
    "errorCount" : 0,
    "errorPct" : 0.0,
    "meanResTime" : 13.0,
    "medianResTime" : 13.0,
    "minResTime" : 13.0,
    "maxResTime" : 13.0,
    "pct1ResTime" : 13.0,
    "pct2ResTime" : 13.0,
    "pct3ResTime" : 13.0,
    "throughput" : 76.92307692307693,
    "receivedKBytesPerSec" : 113.2061298076923,
    "sentKBytesPerSec" : 90.8954326923077
  },
  "Total" : {
    "transaction" : "Total",
    "sampleCount" : 9,
    "errorCount" : 0,
    "errorPct" : 0.0,
    "meanResTime" : 50.11111111111111,
    "medianResTime" : 11.0,
    "minResTime" : 1.0,
    "maxResTime" : 344.0,
    "pct1ResTime" : 344.0,
    "pct2ResTime" : 344.0,
    "pct3ResTime" : 344.0,
    "throughput" : 20.689655172413794,
    "receivedKBytesPerSec" : 61.26751077586207,
    "sentKBytesPerSec" : 24.31303879310345
  },
  "/logout-73-0" : {
    "transaction" : "/logout-73-0",
    "sampleCount" : 1,
    "errorCount" : 0,
    "errorPct" : 0.0,
    "meanResTime" : 11.0,
    "medianResTime" : 11.0,
    "minResTime" : 11.0,
    "maxResTime" : 11.0,
    "pct1ResTime" : 11.0,
    "pct2ResTime" : 11.0,
    "pct3ResTime" : 11.0,
    "throughput" : 90.9090909090909,
    "receivedKBytesPerSec" : 130.859375,
    "sentKBytesPerSec" : 96.05823863636364
  },
  "/login-52 - multiple reg ex" : {
    "transaction" : "/login-52 - multiple reg ex",
    "sampleCount" : 1,
    "errorCount" : 0,
    "errorPct" : 0.0,
    "meanResTime" : 344.0,
    "medianResTime" : 344.0,
    "minResTime" : 344.0,
    "maxResTime" : 344.0,
    "pct1ResTime" : 344.0,
    "pct2ResTime" : 344.0,
    "pct3ResTime" : 344.0,
    "throughput" : 2.9069767441860463,
    "receivedKBytesPerSec" : 10.574695675872094,
    "sentKBytesPerSec" : 1.325740370639535
  },
  "/logout-73" : {
    "transaction" : "/logout-73",
    "sampleCount" : 1,
    "errorCount" : 0,
    "errorPct" : 0.0,
    "meanResTime" : 23.0,
    "medianResTime" : 23.0,
    "minResTime" : 23.0,
    "maxResTime" : 23.0,
    "pct1ResTime" : 23.0,
    "pct2ResTime" : 23.0,
    "pct3ResTime" : 23.0,
    "throughput" : 43.47826086956522,
    "receivedKBytesPerSec" : 228.515625,
    "sentKBytesPerSec" : 93.24048913043478
  },
  "/logout-73-1" : {
    "transaction" : "/logout-73-1",
    "sampleCount" : 1,
    "errorCount" : 0,
    "errorPct" : 0.0,
    "meanResTime" : 11.0,
    "medianResTime" : 11.0,
    "minResTime" : 11.0,
    "maxResTime" : 11.0,
    "pct1ResTime" : 11.0,
    "pct2ResTime" : 11.0,
    "pct3ResTime" : 11.0,
    "throughput" : 90.9090909090909,
    "receivedKBytesPerSec" : 346.94602272727275,
    "sentKBytesPerSec" : 98.89914772727273
  }
}